LICENSE
README.md
pyproject.toml
setup.cfg
superset_client.egg-info/PKG-INFO
superset_client.egg-info/SOURCES.txt
superset_client.egg-info/dependency_links.txt
superset_client.egg-info/requires.txt
superset_client.egg-info/top_level.txt
supersetapiclient/__init__.py
supersetapiclient/assets.py
supersetapiclient/base.py
supersetapiclient/charts.py
supersetapiclient/client.py
supersetapiclient/dashboards.py
supersetapiclient/databases.py
supersetapiclient/datasets.py
supersetapiclient/exceptions.py
supersetapiclient/saved_queries.py