Metadata-Version: 2.1
Name: superset-client
Version: 1.0.0
Summary: A simple REST API Client for Apache-Superset
Author: ciusji
Classifier: Development Status :: 3 - Alpha
Requires-Python: >=3.6
Provides-Extra: dev
Provides-Extra: build
License-File: LICENSE
